{"id":2670627,"name":"Street Photography: Capturing Unique Images","slug":"street-photography-capturing-unique-images","subtitle":null,"product_id":2875041,"description":"Find And Capture Intimate And Interesting Moments In Any City","intro_video_youtube":null,"contact_information":null,"keywords":null,"duration":null,"banner_image_url":"/assets/tenant/default-course-banner.jpg","course_card_image_url":"https://import.cdn.thinkific.com/114242/7qbiE686QDOQIxdmB8md_landing-page-hero-image-180812_stevesweatpants_waystocaptureuniquestreetphotography_christinemarucci_digitalweb_1600x900_final.jpg","intro_video_wistia_identifier":null,"administrator_user_ids":[],"user_id":179230046,"reviews_enabled":true,"instructor_id":1086906,"chapter_ids":[12191132,12191152,12191155],"course_card_text":null}